aphylogeo/__init__.py
aphylogeo/alignement.py
aphylogeo/bin/tmp/a.out
aphylogeo/genetic_trees.py
aphylogeo/main.py
aphylogeo/multiProcessor.py
aphylogeo/params.py
aphylogeo/params.yaml
aphylogeo/preprocessing.py
aphylogeo/requirements.txt
aphylogeo/utils.py
aphylogeo-2.0.0.dist-info/LICENSE
aphylogeo-2.0.0.dist-info/LICENSE.extensions
aphylogeo-2.0.0.dist-info/METADATA
aphylogeo-2.0.0.dist-info/WHEEL
aphylogeo-2.0.0.dist-info/RECORD
