Metadata-Version: 2.1
Name: aphylogeo
Version: 2.0.0
Summary: A phylogenetic and geographic analysis tool
Home-page: https://github.com/tahiri-lab/aPhyloGeo
License: MIT
Author: 'Tahiri Lab'
Requires-Python: >=3.10
Classifier: License :: OSI Approved :: MIT License
Classifier: Programming Language :: Python :: 3
Classifier: Programming Language :: Python :: 3.10
Classifier: Programming Language :: Python :: 3.11
Requires-Dist: bio (>=1.5.9,<2.0.0)
Requires-Dist: cython (>=3.0.2,<4.0.0)
Requires-Dist: dendropy (>=4.6.1,<5.0.0)
Requires-Dist: ete3 (>=3.1.3,<4.0.0)
Requires-Dist: multiprocess (>=0.70.15,<0.71.0)
Requires-Dist: numpy (>=1.26.0,<2.0.0)
Requires-Dist: pandas (>=2.1.1,<3.0.0)
Requires-Dist: psutil (>=5.9.5,<6.0.0)
Requires-Dist: pytest (>=7.4.2,<8.0.0)
Requires-Dist: pyyaml (>=6.0.1,<7.0.0)
Requires-Dist: robinson-foulds (>=1.2,<2.0)
Requires-Dist: scikit-bio (>=0.7.0,<0.8.0)
Requires-Dist: scikit-learn (>=1.7.1,<2.0.0)
Requires-Dist: scipy (>=1.11.4,<2.0.0)
Requires-Dist: textdistance (>=4.6.0,<5.0.0)
Requires-Dist: typer (>=0.13.1,<0.14.0)
Project-URL: Repository, https://github.com/tahiri-lab/aPhyloGeo
